Workbook

Sheet COCOCART INDIA REVENUE REPORT

Sheet COCOCARTINDIA CUSTOMER ANALYSIS
A3: Sum of Amount | C3: Revenue | G3: Months | H3: Revenue | K3: Product Type | L3: Revenue | O3: Distribution | P3: Revenue
A4: 86806888 | C4: =A4 -> 86806888 | G4: Apr | H4: 18981403 | K4: Assorted Chocolates | L4: 12648405 | O4: Offline | P4: 57899443
G5: May | H5: 6619046 | K5: Biscuits & Spreads | L5: 7596708 | O5: Online | P5: 28907445
G6: Jun | H6: 5518849 | K6: Coffee & Hot Chocolate | L6: 5005924 | O6: Grand Total | P6: 86806888
G7: Jul | H7: 5606916 | K7: Dark Chocolates | L7: 12998552
A8: Sum of Total Cost | C8: Cost | G8: Aug | H8: 38678542 | K8: Dry Fruits | L8: 1262044
A9: 26726157 | C9: =A9 -> 26726157 | G9: Sep | H9: 11402132 | K9: Milk Chocolates | L9: 12580918
G10: Grand Total | H10: 86806888 | K10: Mints, Candies & Gums | L10: 1371013
K11: Protein & Energy Bars | L11: 4943470
K12: Sugar Free Chocolates | L12: 10376569 | O12: Store Type | P12: Revenue
A13: Sum of Customers | C13: Customers | K13: Vegan Chocolates | L13: 5096931 | O13: Coco Café | P13: 26454729
A14: 2470776 | C14: =A14 -> 2470776 | K14: White Chocolates | L14: 12926354 | O14: Coco Cart | P14: 60352159
K15: Grand Total | L15: 86806888 | O15: Grand Total | P15: 86806888
A18: Average of Cost per Box | C18: Average Cost | G18: Segment | H18: Revenue | K18: Locations | L18: Revenue | O18: Products | P18: Revenue
A19: 4.9486021 | C19: =A19 -> 4.9486021 | G19: Café | H19: 28881692 | K19: Ahemdabad | L19: 1747977 | O19: 50% Dark Bites | P19: 4121292
G20: E-Commerce | H20: 7141463 | K20: Bangalore | L20: 8758337 | O20: 85% Dark Bars | P20: 4063976
G21: Rapid Stores | H21: 29017751 | K21: Chennai | L21: 1718801 | O21: 99% Dark & Pure | P21: 4357248
G22: Website | H22: 21765982 | K22: Cochin | L22: 1702764 | O22: After Eight | P22: 4108216
A23: Sum of Total Profit | C23: Profit | G23: Grand Total | H23: 86806888 | K23: Indore | L23: 1719242 | O23: Almond Choco | P23: 3980200
A24: 60080731 | C24: =A24 -> 60080731 | K24: Jaipur | L24: 3511914 | O24: Caramel Stuffed Bars | P24: 3976084
K25: Karjat | L25: 3553242 | O25: Choco Coated Almonds | P25: 4300436
K26: Kerala | L26: 3548146 | O26: Organic Choco Syrup | P26: 4188044
K27: Kolkata | L27: 11975173 | O27: Raspberry Choco | P27: 4020184
A28: Sum of Profit % | C28: Profit % | K28: Lucknow | L28: 3498768 | O28: Spicy Special Slims | P28: 4117960
A29: 0.69211939 | C29: =A29 -> 0.69211939 | K29: Mopa | L29: 1697934 | O29: Grand Total | P29: 41233640
K30: Mumbai | L30: 33004468
K31: Navi Mumbai | L31: 3564736
K32: Pune | L32: 3382708
K33: Raigad | L33: 3422678
K34: Grand Total | L34: 86806888

Sheet COCOCART INDIA REVENUE ANALYSIS
A3: Sum of Amount | C3: Revenue | G3: Months | H3: Revenue | K3: Product Type | L3: Revenue | O3: Distribution | P3: Revenue
A4: 86806888 | C4: =A4 -> 86806888 | G4: Apr | H4: 18981403 | K4: Assorted Chocolates | L4: 12648405 | O4: Offline | P4: 57899443
G5: May | H5: 6619046 | K5: Biscuits & Spreads | L5: 7596708 | O5: Online | P5: 28907445
G6: Jun | H6: 5518849 | K6: Coffee & Hot Chocolate | L6: 5005924 | O6: Grand Total | P6: 86806888
G7: Jul | H7: 5606916 | K7: Dark Chocolates | L7: 12998552
A8: Sum of Total Cost | C8: Cost | G8: Aug | H8: 38678542 | K8: Dry Fruits | L8: 1262044
A9: 26726157 | C9: =A9 -> 26726157 | G9: Sep | H9: 11402132 | K9: Milk Chocolates | L9: 12580918
G10: Grand Total | H10: 86806888 | K10: Mints, Candies & Gums | L10: 1371013
K11: Protein & Energy Bars | L11: 4943470
K12: Sugar Free Chocolates | L12: 10376569 | O12: Store Type | P12: Revenue
A13: Sum of Customers | C13: Customers | K13: Vegan Chocolates | L13: 5096931 | O13: Coco Café | P13: 26454729
A14: 2470776 | C14: =A14 -> 2470776 | K14: White Chocolates | L14: 12926354 | O14: Coco Cart | P14: 60352159
K15: Grand Total | L15: 86806888 | O15: Grand Total | P15: 86806888
A18: Average of Cost per Box | C18: Average Cost | G18: Segment | H18: Revenue | K18: Locations | L18: Revenue | O18: Products | P18: Revenue
A19: 4.9486021 | C19: =A19 -> 4.9486021 | G19: Café | H19: 28881692 | K19: Ahemdabad | L19: 1747977 | O19: 50% Dark Bites | P19: 4121292
G20: E-Commerce | H20: 7141463 | K20: Bangalore | L20: 8758337 | O20: 85% Dark Bars | P20: 4063976
G21: Rapid Stores | H21: 29017751 | K21: Chennai | L21: 1718801 | O21: 99% Dark & Pure | P21: 4357248
G22: Website | H22: 21765982 | K22: Cochin | L22: 1702764 | O22: After Eight | P22: 4108216
A23: Sum of Total Profit | C23: Profit | G23: Grand Total | H23: 86806888 | K23: Indore | L23: 1719242 | O23: Almond Choco | P23: 3980200
A24: 60080731 | C24: =A24 -> 60080731 | K24: Jaipur | L24: 3511914 | O24: Caramel Stuffed Bars | P24: 3976084
K25: Karjat | L25: 3553242 | O25: Choco Coated Almonds | P25: 4300436
K26: Kerala | L26: 3548146 | O26: Organic Choco Syrup | P26: 4188044
K27: Kolkata | L27: 11975173 | O27: Raspberry Choco | P27: 4020184
A28: Sum of Profit % | C28: Profit % | K28: Lucknow | L28: 3498768 | O28: Spicy Special Slims | P28: 4117960
A29: 0.69211939 | C29: =A29 -> 0.69211939 | K29: Mopa | L29: 1697934 | O29: Grand Total | P29: 41233640
K30: Mumbai | L30: 33004468
K31: Navi Mumbai | L31: 3564736
K32: Pune | L32: 3382708
K33: Raigad | L33: 3422678
K34: Grand Total | L34: 86806888

Sheet COCOCART INDIA DATA
A1: Product ID | B1: Sales Person | C1: Locations | D1: Store Type | E1: Distribution Channel | F1: Segment | G1: Product | H1: Product Type | I1: Date | J1: Amount | K1: Customers | L1: Boxes | M1: Brands | N1: Category | O1: Size | P1: Cost per Box | Q1: Total Cost | R1: Month No. | S1: Months | T1: Day No. | U1: Week Day
A2: 2400040009 | B2: Barr Faughny | C2: Bangalore | D2: Coco Café | E2: Online | F2: E-Commerce | G2: Raspberry Choco | H2: Milk Chocolates | I2: 45748 | J2: 8414 | K2: 276 | L2: 495 | M2: After Eight | N2: Bars | O2: Large | P2: 6.0983 | Q2: 3018.6585 | R2: =MONTH('COCOCART INDIA DATA'!$I2) -> 4 | S2: =TEXT(Table2[[#This Row],[Date]],"mmm") -> Apr | T2: =DAY(Table2[[#This Row],[Date]]) -> 1 | U2: =TEXT(Table2[[#This Row],[Date]],"ddd") -> Tue
A3: 2400040010 | B3: Dennison Crosswaite | C3: Bangalore | D3: Coco Cart | E3: Online | F3: Website | G3: White Choc | H3: Dark Chocolates | I3: 45748 | J3: 532 | K3: 317 | L3: 54 | M3: Angelina | N3: Other | O3: Small | P3: 0.2405 | Q3: 12.987 | R3: =MONTH('COCOCART INDIA DATA'!$I3) -> 4 | S3: =TEXT(Table2[[#This Row],[Date]],"mmm") -> Apr | T3: =DAY(Table2[[#This Row],[Date]]) -> 1 | U3: =TEXT(Table2[[#This Row],[Date]],"ddd") -> Tue
A4: 2400040011 | B4: Karlen McCaffrey | C4: Bangalore | D4: Coco Café | E4: Offline | F4: Café | G4: 99% Dark & Pure | H4: White Chocolates | I4: 45748 | J4: 5376 | K4: 178 | L4: 269 | M4: Anthon Berg | N4: Bars | O4: Large | P4: 4.6592 | Q4: 1253.3248 | R4: =MONTH('COCOCART INDIA DATA'!$I4) -> 4 | S4: =TEXT(Table2[[#This Row],[Date]],"mmm") -> Apr | T4: =DAY(Table2[[#This Row],[Date]]) -> 1 | U4: =TEXT(Table2[[#This Row],[Date]],"ddd") -> Tue
A5: 2400040012 | B5: Barr Faughny | C5: Bangalore | D5: Coco Cart | E5: Offline | F5: Rapid Stores | G5: Baker's Choco Chips | H5: Biscuits & Spreads | I5: 45748 | J5: 259 | K5: 32 | L5: 22 | M5: Bounty | N5: Bars | O5: Small | P5: 6.0811 | Q5: 133.7842 | R5: =MONTH('COCOCART INDIA DATA'!$I5) -> 4 | S5: =TEXT(Table2[[#This Row],[Date]],"mmm") -> Apr | T5: =DAY(Table2[[#This Row],[Date]]) -> 1 | U5: =TEXT(Table2[[#This Row],[Date]],"ddd") -> Tue
A6: 2400040013 | B6: Beverie Moffet | C6: Bangalore | D6: Coco Cart | E6: Offline | F6: Café | G6: Manuka Honey Choco | H6: Coffee & Hot Chocolate | I6: 45748 | J6: 5530 | K6: 4 | L6: 179 | M6: Butlers | N6: Other | O6: Small | P6: 7.8911 | Q6: 1412.5069 | R6: =MONTH('COCOCART INDIA DATA'!$I6) -> 4 | S6: =TEXT(Table2[[#This Row],[Date]],"mmm") -> Apr | T6: =DAY(Table2[[#This Row],[Date]]) -> 1 | U6: =TEXT(Table2[[#This Row],[Date]],"ddd") -> Tue
A7: 2400040014 | B7: Rafaelita Blaksland | C7: Chennai | D7: Coco Cart | E7: Offline | F7: Rapid Stores | G7: 85% Dark Bars | H7: Protein & Energy Bars | I7: 45748 | J7: 2184 | K7: 63 | L7: 122 | M7: Cadbury | N7: Bars | O7: Small | P7: 0.6958 | Q7: 84.8876 | R7: =MONTH('COCOCART INDIA DATA'!$I7) -> 4 | S7: =TEXT(Table2[[#This Row],[Date]],"mmm") -> Apr | T7: =DAY(Table2[[#This Row],[Date]]) -> 1 | U7: =TEXT(Table2[[#This Row],[Date]],"ddd") -> Tue
A8: 2400040015 | B8: Oby Sorrel | C8: Cochin | D8: Coco Cart | E8: Online | F8: Website | G8: Raspberry Choco | H8: Vegan Chocolates | I8: 45748 | J8: 1057 | K8: 295 | L8: 71 | M8: Caprice | N8: Bars | O8: Large | P8: 6.0983 | Q8: 432.9793 | R8: =MONTH('COCOCART INDIA DATA'!$I8) -> 4 | S8: =TEXT(Table2[[#This Row],[Date]],"mmm") -> Apr | T8: =DAY(Table2[[#This Row],[Date]]) -> 1 | U8: =TEXT(Table2[[#This Row],[Date]],"ddd") -> Tue
A9: 2400040016 | B9: Dotty Strutley | C9: Mopa | D9: Coco Cart | E9: Online | F9: Website | G9: Organic Choco Syrup | H9: Sugar Free Chocolates | I9: 45748 | J9: 1036 | K9: 370 | L9: 37 | M9: Cartwright & Butler | N9: Other | O9: Small | P9: 1.7625 | Q9: 65.2125 | R9: =MONTH('COCOCART INDIA DATA'!$I9) -> 4 | S9: =TEXT(Table2[[#This Row],[Date]],"mmm") -> Apr | T9: =DAY(Table2[[#This Row],[Date]]) -> 1 | U9: =TEXT(Table2[[#This Row],[Date]],"ddd") -> Tue
A10: 2400040017 | B10: Brien Boise | C10: Kerala | D10: Coco Cart | E10: Offline | F10: Café | G10: Caramel Stuffed Bars | H10: Assorted Chocolates | I10: 45748 | J10: 4039 | K10: 536 | L10: 176 | M10: Cavendish | N10: Bars | O10: Small | P10: 0.899 | Q10: 158.224 | R10: =MONTH('COCOCART INDIA DATA'!$I10) -> 4 | S10: =TEXT(Table2[[#This Row],[Date]],"mmm") -> Apr | T10: =DAY(Table2[[#This Row],[Date]]) -> 1 | U10: =TEXT(Table2[[#This Row],[Date]],"ddd") -> Tue
A11: 2400040018 | B11: Curtice Advani | C11: Kerala | D11: Coco Cart | E11: Offline | F11: Rapid Stores | G11: Milk Bars | H11: Mints, Candies & Gums | I11: 45748 | J11: 12894 | K11: 115 | L11: 478 | M11: Chocodate | N11: Bars | O11: Large | P11: 1.8652 | Q11: 891.5656 | R11: =MONTH('COCOCART INDIA DATA'!$I11) -> 4 | S11: =TEXT(Table2[[#This Row],[Date]],"mmm") -> Apr | T11: =DAY(Table2[[#This Row],[Date]]) -> 1 | U11: =TEXT(Table2[[#This Row],[Date]],"ddd") -> Tue
A12: 2400040019 | B12: Madelene Upcott | C12: Pune | D12: Coco Café | E12: Offline | F12: Café | G12: Milk Bars | H12: Dry Fruits | I12: 45748 | J12: 4669 | K12: 121 | L12: 180 | M12: Chupa Chups | N12: Bars | O12: Large | P12: 1.8652 | Q12: 335.736 | R12: =MONTH('COCOCART INDIA DATA'!$I12) -> 4 | S12: =TEXT(Table2[[#This Row],[Date]],"mmm") -> Apr | T12: =DAY(Table2[[#This Row],[Date]]) -> 1 | U12: =TEXT(Table2[[#This Row],[Date]],"ddd") -> Tue
A13: 2400040020 | B13: Wilone O'Kielt | C13: Pune | D13: Coco Cart | E13: Offline | F13: Rapid Stores | G13: Organic Choco Syrup | H13: Coffee & Hot Chocolate | I13: 45748 | J13: 6377 | K13: 184 | L13: 246 | M13: Elvan | N13: Other | O13: Small | P13: 1.7625 | Q13: 433.575 | R13: =MONTH('COCOCART INDIA DATA'!$I13) -> 4 | S13: =TEXT(Table2[[#This Row],[Date]],"mmm") -> Apr | T13: =DAY(Table2[[#This Row],[Date]]) -> 1 | U13: =TEXT(Table2[[#This Row],[Date]],"ddd") -> Tue
... A15165: 2400055172 | B15165: Mallorie Waber | C15165: Karjat | D15165: Coco Café | E15165: Online | F15165: Website | G15165: Spicy Special Slims | H15165: Vegan Chocolates | I15165: 45930 | J15165: 3871 | K15165: 338 | L15165: 431 | M15165: Rhine Valley | N15165: Bites | O15165: Large | P15165: 9.2086 | Q15165: 3968.9066 | R15165: =MONTH('COCOCART INDIA DATA'!$I15165) -> 9 | S15165: =TEXT(Table2[[#This Row],[Date]],"mmm") -> Sep | T15165: =DAY(Table2[[#This Row],[Date]]) -> 30 | U15165: =TEXT(Table2[[#This Row],[Date]],"ddd") -> Tue
